poseutils/__init__.py
poseutils/camera_utils.py
poseutils/common.py
poseutils/composite.py
poseutils/constants.py
poseutils/logger.py
poseutils/metrics.py
poseutils/props.py
poseutils/transform.py
poseutils/view.py
poseutils/datasets/__init__.py
poseutils/datasets/processed/TransformedDataset.py
poseutils/datasets/processed/__init__.py
poseutils/datasets/transformation/CalculateMetrics.py
poseutils/datasets/transformation/CropAndScale.py
poseutils/datasets/transformation/Normalize.py
poseutils/datasets/transformation/RootCenter.py
poseutils/datasets/transformation/Transformation.py
poseutils/datasets/transformation/Unnormalize.py
poseutils/datasets/transformation/__init__.py
poseutils/datasets/unprocessed/Dataset.py
poseutils/datasets/unprocessed/GPADataset.py
poseutils/datasets/unprocessed/H36MDataset.py
poseutils/datasets/unprocessed/MPI3DHPDataset.py
poseutils/datasets/unprocessed/SURREALDataset.py
poseutils/datasets/unprocessed/TDPWDataset.py
poseutils/datasets/unprocessed/__init__.py
poseutils-0.4.0.dist-info/licenses/LICENSE.txt
poseutils-0.4.0.dist-info/METADATA
poseutils-0.4.0.dist-info/WHEEL
poseutils-0.4.0.dist-info/top_level.txt
poseutils-0.4.0.dist-info/RECORD
